isopy/__init__.py
isopy/array_functions.py
isopy/checks.py
isopy/core.py
isopy/io.py
isopy/reference_values.py
isopy/tb.py
isopy/referencedata/element_atomic_number.csv
isopy/referencedata/element_initial_solar_system_abundance_L09.csv
isopy/referencedata/element_symbol_name.csv
isopy/referencedata/isotope_best_measurement_fraction_M16.csv
isopy/referencedata/isotope_initial_solar_system_abundance_AG89.csv
isopy/referencedata/isotope_initial_solar_system_abundance_L09.csv
isopy/referencedata/isotope_initial_solar_system_fraction_L09.csv
isopy/referencedata/isotope_mass_AME20.csv
isopy/referencedata/isotope_mass_W17.csv
isopy/referencedata/isotope_present_solar_system_abundance_AG89.csv
isopy/referencedata/isotope_present_solar_system_fraction_AG89.csv
isopy/referencedata/isotope_sprocess_fraction_B11.csv
isopy/toolbox/__init__.py
isopy/toolbox/doublespike.py
isopy/toolbox/isotope.py
isopy/toolbox/plot.py
isopy/toolbox/regress.py
isopy-0.7.8.dist-info/LICENSE.txt
isopy-0.7.8.dist-info/METADATA
isopy-0.7.8.dist-info/WHEEL
isopy-0.7.8.dist-info/top_level.txt
isopy-0.7.8.dist-info/RECORD
