Metadata-Version: 2.1
Name: isopy
Version: 0.7.8
Summary: A Python 3 library for data processing in isotope geo/cosmochemistry.
Home-page: https://github.com/mattias-ek/isopy
Author: Mattias Ek
Author-email: mattias.ek@erdw.ethz.ch
Keywords: array isotope geochemistry cosmochemisty geology icpms icp-ms
Classifier: Programming Language :: Python :: 3
Classifier: License :: OSI Approved :: MIT License
Classifier: Operating System :: OS Independent
Classifier: Development Status :: 4 - Beta
Classifier: Intended Audience :: Education
Requires-Python: >=3.9
License-File: LICENSE.txt
Requires-Dist: numpy (>=1.20)
Requires-Dist: pyperclip (>=1.8)
Requires-Dist: openpyxl (>=3)
Requires-Dist: matplotlib (>=3.3)
Requires-Dist: scipy (>=1.6)
Requires-Dist: chardet (>=4)
Requires-Dist: tabulate (>=0.8)
